{
	"ci": {
		"collect": {
			"numberOfRuns": 3,
			"staticDistDir": "./dist",
			"url": ["/"]
		},
		"assert": {
			"preset": "lighthouse:recommended",
			"assertions": {
				"apple-touch-icon": "off",
				"crawlable-anchors": "off",
				"csp-xss": "off",
				"html-has-lang": "off",
				"installable-manifest": "off",
				"link-name": "off",
				"maskable-icon": "off",
				"meta-description": "off",
				"service-worker": "off",
				"splash-screen": "off",
				"non-composited-animations": "off",
				"themed-omnibox": "off",
				"canonical": "off",
				"content-width": "off",
				"external-anchors-use-rel-noopener": "off"
			}
		},
		"upload": {
			"target": "temporary-public-storage"
		},
		"server": {},
		"wizard": {}
	}
}
